builder/__init__.py
builder/builder.py
grafana_dashboards_builder-0.3.1.dist-info/entry_points.txt
grafana_dashboards_builder-0.3.1.dist-info/LICENSE
grafana_dashboards_builder-0.3.1.dist-info/WHEEL
grafana_dashboards_builder-0.3.1.dist-info/METADATA
grafana_dashboards_builder-0.3.1.dist-info/RECORD
