Metadata-Version: 2.1
Name: grafana-dashboards-builder
Version: 0.3.1
Summary: A wrapper around grafanalib which simplifies generating multiple dashboards.
Home-page: https://gitlab.com/grdl/grafana-dashboards-builder
License: MIT
Keywords: grafana,grafanalib
Author: Grzegorz Dlugoszewski
Author-email: pypi@grdl.dev
Maintainer: Grzegorz Dlugoszewski
Maintainer-email: pypi@grdl.dev
Requires-Python: >=3.6,<4.0
Classifier: License :: OSI Approved :: MIT License
Classifier: Programming Language :: Python :: 3
Classifier: Programming Language :: Python :: 3.6
Classifier: Programming Language :: Python :: 3.7
Classifier: Programming Language :: Python :: 3.8
Requires-Dist: click (>=7.1.1,<8.0.0)
Requires-Dist: grafanalib (>=0.5.5,<0.6.0)
Project-URL: Repository, https://gitlab.com/grdl/grafana-dashboards-builder
